Metadata-Version: 2.1
Name: polyfasNast
Version: 1.2
Summary: Класс для работы с файлами
Author-email: khavrotinan@gmail.com
